conflex/__init__.py
conflex/main.py
conflex-0.0.0a3.dist-info/LICENSE.txt
conflex-0.0.0a3.dist-info/METADATA
conflex-0.0.0a3.dist-info/WHEEL
conflex-0.0.0a3.dist-info/top_level.txt
conflex-0.0.0a3.dist-info/RECORD
