Metadata-Version: 2.1
Name: conflex
Version: 0.0.0a3
Summary: Flexible and extensible configuration reader for python.
Home-page: https://github.com/TEH30P/conflex
Author: TEH3OP
Author-email: TEH3OP@gmail.com
License: MIT
Keywords: configuration parser development
Platform: UNKNOWN
Classifier: Development Status :: 3 - Alpha
Classifier: Intended Audience :: Developers
Classifier: Intended Audience :: Education
Classifier: License :: OSI Approved :: MIT License
Classifier: Programming Language :: Python :: 3
Classifier: Programming Language :: Python :: 3.5
Classifier: Programming Language :: Python :: 3.6
Classifier: Programming Language :: Python :: 3.7
Classifier: Programming Language :: Python :: 3.8
Classifier: Programming Language :: Python :: 3.9
Classifier: Topic :: Software Development
Classifier: Topic :: Software Development :: Libraries
Classifier: Topic :: Software Development :: Libraries :: Python Modules
Requires-Python: >=3.6.0
License-File: LICENSE.txt
Provides-Extra: testing
Requires-Dist: pytest (>=5.3.5) ; extra == 'testing'
Requires-Dist: pytest-cov (>=2.8.1) ; extra == 'testing'
Requires-Dist: mypy ; extra == 'testing'
